skill_messaging/LICENSE.md
skill_messaging/README.md
skill_messaging/__init__.py
skill_messaging/skill.json
skill_messaging/version.py
skill_messaging/version_bump.py
skill_messaging/dialog/en-us/ConfirmCall.dialog
skill_messaging/dialog/en-us/ConfirmEmail.dialog
skill_messaging/dialog/en-us/ConfirmMessage.dialog
skill_messaging/dialog/en-us/ConfirmSend.dialog
skill_messaging/dialog/en-us/ContactNotFound.dialog
skill_messaging/dialog/en-us/DiscardDraft.dialog
skill_messaging/dialog/en-us/EmailSent.dialog
skill_messaging/dialog/en-us/ErrorDialog.dialog
skill_messaging/dialog/en-us/GetEmailBody.dialog
skill_messaging/dialog/en-us/GetEmailSubject.dialog
skill_messaging/dialog/en-us/GetRecipientAddress.dialog
skill_messaging/dialog/en-us/OnlyMobile.dialog
skill_messaging/dialog/en-us/TextSent.dialog
skill_messaging/neon_skill_messaging.egg-info/PKG-INFO
skill_messaging/neon_skill_messaging.egg-info/SOURCES.txt
skill_messaging/neon_skill_messaging.egg-info/dependency_links.txt
skill_messaging/neon_skill_messaging.egg-info/entry_points.txt
skill_messaging/neon_skill_messaging.egg-info/requires.txt
skill_messaging/neon_skill_messaging.egg-info/top_level.txt
skill_messaging/vocab/en-us/Neon.voc
skill_messaging/vocab/en-us/draft.voc
skill_messaging/vocab/en-us/email.voc
skill_messaging/vocab/en-us/klat.voc
skill_messaging/vocab/en-us/message.voc
skill_messaging/vocab/en-us/no.voc
skill_messaging/vocab/en-us/sms.voc
skill_messaging/vocab/en-us/yes.voc
neon_skill_messaging-0.0.1.dist-info/LICENSE.md
neon_skill_messaging-0.0.1.dist-info/METADATA
neon_skill_messaging-0.0.1.dist-info/WHEEL
neon_skill_messaging-0.0.1.dist-info/entry_points.txt
neon_skill_messaging-0.0.1.dist-info/top_level.txt
neon_skill_messaging-0.0.1.dist-info/RECORD
