Metadata-Version: 2.1
Name: neon-skill-messaging
Version: 0.0.1
Summary: UNKNOWN
Home-page: https://github.com/NeonGeckoCom/skill-messaging
Author: Neongecko
Author-email: developers@neon.ai
License: BSD-3-Clause
Platform: UNKNOWN
Requires-Dist: phonenumbers (~=8.12)
Requires-Dist: neon-utils (<2.0.0,>=0.6)
